{
  "updated_at": "2026-07-14T10:17:35.986635+00:00",
  "count": 72,
  "items": [
    {
      "source": "r/Forex",
      "category": "reddit",
      "title": "Thoughts on XAUUSD?",
      "summary": "<table> <tr><td> <a href=\"https://www.reddit.com/r/Forex/comments/1uw4lgj/thoughts_on_xauusd/\"> <img alt=\"Thoughts on XAUUSD?\" src=\"https://preview.redd.it/jj8n3tyw76dh1.jpeg?width=640&amp;crop=smart&amp;auto=webp&amp;s=616854da6f10c0def914297662d9c045c6974771\" title=\"Thoughts on XAUUSD?\" /> </a> </td><td> <!-- SC_OFF --><div class=\"md\"><p>I am expecting lower prices towards the sellside liquidity",
      "link": "https://www.reddit.com/r/Forex/comments/1uw4lgj/thoughts_on_xauusd/",
      "published": "2026-07-14T10:16:50+00:00",
      "score": 3
    },
    {
      "source": "r/Forex",
      "category": "reddit",
      "title": "S&p 500 outlook",
      "summary": "<table> <tr><td> <a href=\"https://www.reddit.com/r/Forex/comments/1uw4bdj/sp_500_outlook/\"> <img alt=\"S&amp;p 500 outlook\" src=\"https://preview.redd.it/s2shrsm656dh1.jpeg?width=640&amp;crop=smart&amp;auto=webp&amp;s=1b6c04230caf68ff9970f376b271532017117190\" title=\"S&amp;p 500 outlook\" /> </a> </td><td> <!-- SC_OFF --><div class=\"md\"><p>Expecting higher prices </p> </div><!-- SC_ON --> &#32; submit",
      "link": "https://www.reddit.com/r/Forex/comments/1uw4bdj/sp_500_outlook/",
      "published": "2026-07-14T10:01:32+00:00",
      "score": 1
    },
    {
      "source": "FXStreet",
      "category": "news",
      "title": "GBP/USD Price Forecast: Pound holds above 1.3350 with the 200-day SMA capping gains",
      "summary": "The British Pound (GBP) appreciates against the US Dollar (USD)  on Tuesday to trim previous losses and return to the 1.3375 area, aiming to retest resistance at the key 200-day Simple Moving Average (SMA).",
      "link": "https://www.fxstreet.com/news/gbp-usd-price-forecast-pound-holds-above-13350-with-the-200-day-sma-capping-gains-202607140957",
      "published": "2026-07-14T09:57:03+00:00",
      "score": 1
    },
    {
      "source": "FXStreet",
      "category": "news",
      "title": "US Dollar: Tailwinds build as oil and Fed reprice – OCBC",
      "summary": "OCBC strategists Sim Moh Siong and Christopher Wong note the US Dollar (USD) has strengthened broadly on higher Oil prices, hawkish Federal Reserve (Fed) rhetoric and softer risk sentiment.",
      "link": "https://www.fxstreet.com/news/us-dollar-tailwinds-build-as-oil-and-fed-reprice-ocbc-202607140953",
      "published": "2026-07-14T09:53:51+00:00",
      "score": 2
    },
    {
      "source": "FXStreet",
      "category": "news",
      "title": "Fed: Guidance, reaction function and rates – BNY",
      "summary": "BNY Markets strategists John Velis and David Tam discuss new Federal Reserve (Fed) task forces and focus on the Communications group led by Mervyn King, Arminio Fraga and Peter Fisher.",
      "link": "https://www.fxstreet.com/news/fed-guidance-reaction-function-and-rates-bny-202607140933",
      "published": "2026-07-14T09:33:45+00:00",
      "score": 2
    },
    {
      "source": "FinancialJuice",
      "category": "news",
      "title": "FinancialJuice: German 2 Yr Schatz Yield Actual 2.77% (Forecast -, Previous 2.57%)",
      "summary": "",
      "link": "https://www.financialjuice.com/News/9676809/German-2-Yr-Schatz-Yield-Actual-277-Forecast---Previous-257.aspx?xy=rss",
      "published": "2026-07-14T09:32:08+00:00",
      "score": 1
    },
    {
      "source": "FXStreet",
      "category": "news",
      "title": "Silver price today: Silver rises, according to FXStreet data",
      "summary": "Silver prices (XAG/USD) rose on Tuesday, according to FXStreet data. Silver trades at $58.08 per troy ounce, up 0.76% from the $57.65 it cost on Monday.",
      "link": "https://www.fxstreet.com/news/silver-price-today-silver-rises-according-to-fxstreet-data-202607140930",
      "published": "2026-07-14T09:30:47+00:00",
      "score": 3
    },
    {
      "source": "FinancialJuice",
      "category": "news",
      "title": "FinancialJuice: MUFG: The JPY - FJElite",
      "summary": "<div>While government bond yields have risen in response to higher energy prices, it has been notable that JGB yields have fallen again overnight. The 10-year and 30-year JGB yields have dropped by 7bps and 16bps respectively. JGBs are deriving more support from verbal intervention from Japanese policymakers indicating that they will encourage domestic investors to increase portfolio allocations t",
      "link": "https://www.financialjuice.com/News/9676796/MUFG-The-JPY---FJElite.aspx?xy=rss",
      "published": "2026-07-14T09:29:47+00:00",
      "score": 1
    },
    {
      "source": "FXStreet",
      "category": "news",
      "title": "Oil: Hormuz risk repricing lifts prices – Rabobank",
      "summary": "Rabobank's Michael Every highlights a sharp Oil rally ahead of United States (US) Consumer Price Index (CPI) and Fed Chair Warsh’s testimony, with prices jumping 9% and then another 2.5% to $85.",
      "link": "https://www.fxstreet.com/news/oil-hormuz-risk-repricing-lifts-prices-rabobank-202607140923",
      "published": "2026-07-14T09:23:07+00:00",
      "score": 2
    },
    {
      "source": "FXStreet",
      "category": "news",
      "title": "Silver Price Forecast: XAG/USD holds above $58.00 despite ongoing bearish bias",
      "summary": "XAG/USD gains ground after two days of losses, trading around $58.10 per troy ounce during the European hours on Tuesday. The technical analysis of the daily chart shows that the spot price is remaining within the descending channel pattern.",
      "link": "https://www.fxstreet.com/news/silver-price-forecast-xag-usd-holds-above-5800-despite-ongoing-bearish-bias-202607140921",
      "published": "2026-07-14T09:21:01+00:00",
      "score": 3
    },
    {
      "source": "FinancialJuice",
      "category": "news",
      "title": "FinancialJuice: Trump is very serious about 20% fee plan for Hormuz - Semafor.",
      "summary": "",
      "link": "https://www.financialjuice.com/News/9676795/Trump-is-very-serious-about-20-fee-plan-for-Hormuz---Semafor.aspx?xy=rss",
      "published": "2026-07-14T09:20:21+00:00",
      "score": 1
    },
    {
      "source": "Walter Bloomberg",
      "category": "twitter",
      "title": "*TRUMP 'VERY SERIOUS' ABOUT 20% FEE PLAN FOR HORMUZ: SEMAFOR",
      "summary": "<p>*TRUMP 'VERY SERIOUS' ABOUT 20% FEE PLAN FOR HORMUZ: SEMAFOR</p>",
      "link": "https://nitter.net/DeItaone/status/2076959630949814404#m",
      "published": "2026-07-14T09:18:58+00:00",
      "score": 1
    },
    {
      "source": "FinancialJuice",
      "category": "news",
      "title": "FinancialJuice: Trump Hormuz toll plan details still being ironed out - Semafor.",
      "summary": "",
      "link": "https://www.financialjuice.com/News/9676794/Trump-Hormuz-toll-plan-details-still-being-ironed-out---Semafor.aspx?xy=rss",
      "published": "2026-07-14T09:18:07+00:00",
      "score": 1
    },
    {
      "source": "FXStreet",
      "category": "news",
      "title": "USD/JPY Price Forecast: Slides to 162.00 as constructive setup favors bulls before US CPI",
      "summary": "The USD/JPY pair remains on the back foot through the first half of the European session on Tuesday. Intervention risks support the Japanese Yen (JPY) and act as a headwind for spot prices amid a softer US Dollar (USD).",
      "link": "https://www.fxstreet.com/news/usd-jpy-price-forecast-slides-to-16200-as-constructive-setup-favors-bulls-before-us-cpi-202607140857",
      "published": "2026-07-14T08:57:30+00:00",
      "score": 2
    },
    {
      "source": "FXStreet",
      "category": "news",
      "title": "US Dollar Index: DXY could reach 102 as Gulf tensions persist - ING",
      "summary": "ING strategists Francesco Pesole, Frantisek Taborsky and Chris Turner note that higher Crude and Gulf tensions are not yet fully priced, leaving short-term upside risks for the US Dollar (USD).",
      "link": "https://www.fxstreet.com/news/us-dollar-index-dxy-could-reach-102-as-gulf-tensions-persist-ing-202607140851",
      "published": "2026-07-14T08:51:12+00:00",
      "score": 2
    },
    {
      "source": "FXStreet",
      "category": "news",
      "title": "New Zealand Dollar holds gains near 0.5800, unfazed by risk aversion",
      "summary": "The New Zealand Dollar (NZD) appreciates against the US Dollar (USD) on Tuesday, hardly affected by the risk-averse scenario.",
      "link": "https://www.fxstreet.com/news/new-zealand-dollar-holds-gains-near-05800-unfazed-by-risk-aversion-202607140849",
      "published": "2026-07-14T08:49:59+00:00",
      "score": 1
    },
    {
      "source": "FXStreet",
      "category": "news",
      "title": "Indian Rupee slumps amid dual pressure from higher oil prices, Treasury yields",
      "summary": "The Indian Rupee trades significantly lower against the US Dollar (USD) on Tuesday. The USD/INR pair posts a fresh seven-week high near 96.13 as surging oil prices and United States (US) Treasury Yields due to threats of levy from Washington have weakened the appeal of the Indian currency.",
      "link": "https://www.fxstreet.com/news/indian-rupee-drifts-sharply-lower-as-us-claims-right-of-hormuz-toll-fee-202607140537",
      "published": "2026-07-14T08:43:25+00:00",
      "score": 2
    },
    {
      "source": "FXStreet",
      "category": "news",
      "title": "Japanese Yen: Stays weak within broad band against US Dollar – UOB",
      "summary": "United Overseas Bank’s Quek Ser Leang and Lee Sue Ann report USD/JPY rebounded from 161.26 to trade between 161.55 and 162.48, closing firm at 162.42. They see scope for a test of 162.70 while keeping 163.00 out of view, with support at 162.20/162.00.",
      "link": "https://www.fxstreet.com/news/japanese-yen-stays-weak-within-broad-band-against-us-dollar-uob-202607140838",
      "published": "2026-07-14T08:38:21+00:00",
      "score": 1
    },
    {
      "source": "FXStreet",
      "category": "news",
      "title": "Euro rises against US Dollar as latter corrects ahead of US CPI data",
      "summary": "The Euro (EUR) trades slightly higher to near 1.1395 against the US Dollar (USD) during the European trading session on Tuesday. The major currency pair gains as the US Dollar corrects ahead of the United States (US) Consumer Price Index (CPI) data for June, which will be published at 12:30 GMT.",
      "link": "https://www.fxstreet.com/news/euro-rises-against-us-dollar-as-latter-corrects-ahead-of-us-cpi-data-202607140838",
      "published": "2026-07-14T08:38:17+00:00",
      "score": 2
    },
    {
      "source": "FinancialJuice",
      "category": "news",
      "title": "FinancialJuice: Credit Ágricole: BoK Meeting - FJElite",
      "summary": "<div><ul><li>The BOK is widely expected to hike its policy rate by 25bp to 2.75% on 16 July. The BOK has reiterated the need for rate hikes several times. Thus, market participants will be watching for the BOK’s hints on the timing of the next hike and the terminal rate for this rate hiking cycle.</li><li>Considering that there will be the BOK’s macro forecast and six-month forward guidance update",
      "link": "https://www.financialjuice.com/News/9676721/Credit-%c3%81gricole-BoK-Meeting---FJElite.aspx?xy=rss",
      "published": "2026-07-14T08:33:41+00:00",
      "score": 1
    },
    {
      "source": "FXStreet",
      "category": "news",
      "title": "US CPI data set to show inflation cooled in June due to tumbling fuel prices",
      "summary": "The US Bureau of Labor Statistics (BLS) will publish the June Consumer Price Index (CPI) data on Tuesday.",
      "link": "https://www.fxstreet.com/news/us-cpi-data-set-to-show-inflation-cooled-in-june-due-to-tumbling-fuel-prices-202607140830",
      "published": "2026-07-14T08:30:00+00:00",
      "score": 2
    },
    {
      "source": "FXStreet",
      "category": "news",
      "title": "Dow Jones futures fall ahead of results from Wall Street lenders",
      "summary": "Dow Jones futures lose 0.26% to trade around 52,620 during European trading hours on Tuesday. Meanwhile, S&amp;P 500 futures and Nasdaq 100 futures fall 0.03% and 0.42%, trading near 7,560 and 29,600, respectively.",
      "link": "https://www.fxstreet.com/news/dow-jones-futures-fall-ahead-of-results-from-wall-street-lenders-202607140825",
      "published": "2026-07-14T08:25:53+00:00",
      "score": 1
    },
    {
      "source": "FXStreet",
      "category": "news",
      "title": "Oil: Stagflation fears rise with Middle East tensions – Deutsche Bank",
      "summary": "Deutsche Bank strategists highlight a sharp jump in Oil prices driven by escalating tensions between the US and Iran and renewed rhetoric from President Trump on the Strait of Hormuz.",
      "link": "https://www.fxstreet.com/news/oil-stagflation-fears-rise-with-middle-east-tensions-deutsche-bank-202607140824",
      "published": "2026-07-14T08:24:16+00:00",
      "score": 1
    },
    {
      "source": "r/Forex",
      "category": "reddit",
      "title": "Fed Waller changed everything",
      "summary": "<table> <tr><td> <a href=\"https://www.reddit.com/r/Forex/comments/1uw2lnn/fed_waller_changed_everything/\"> <img alt=\"Fed Waller changed everything\" src=\"https://preview.redd.it/dycv12lan5dh1.jpg?width=140&amp;height=98&amp;auto=webp&amp;s=88bb92ad3890014396588c8fa0bee0d790c88a3e\" title=\"Fed Waller changed everything\" /> </a> </td><td> <!-- SC_OFF --><div class=\"md\"><p>Hope DXY behaves this week. I",
      "link": "https://www.reddit.com/r/Forex/comments/1uw2lnn/fed_waller_changed_everything/",
      "published": "2026-07-14T08:21:18+00:00",
      "score": 2
    },
    {
      "source": "FinancialJuice",
      "category": "news",
      "title": "FinancialJuice: 83% of investors do not expect Fed to hike rates before November US midterm elections - BofA FMS",
      "summary": "",
      "link": "https://www.financialjuice.com/News/9676634/83-of-investors-do-not-expect-Fed-to-hike-rates-before-November-US-midterm-elections---BofA-FMS.aspx?xy=rss",
      "published": "2026-07-14T07:19:11+00:00",
      "score": 2
    },
    {
      "source": "Kobeissi Letter",
      "category": "twitter",
      "title": "BREAKING: US oil prices officially surge above $80/barrel as President Trump reimposes the US blockade of the Strait of Hormuz and the Iran War resumes.",
      "summary": "<p>BREAKING: US oil prices officially surge above $80/barrel as President Trump reimposes the US blockade of the Strait of Hormuz and the Iran War resumes.</p>\n<img src=\"https://nitter.net/pic/media%2FHNJdrj3WIAA5Ls0.png\" />",
      "link": "https://nitter.net/KobeissiLetter/status/2076825415339929898#m",
      "published": "2026-07-14T00:25:39+00:00",
      "score": 1
    },
    {
      "source": "Kobeissi Letter",
      "category": "twitter",
      "title": "Risk appetite is reaching historic levels: The 10-day moving average of S&P 500 options volume is up to a record ~5.5 million contracts. Since 2022, this figure has more than TRIPLED. Over the same period, Euro Stoxx 50 options volume has remained roughly unchanged, near ~1 million contracts. As a result, US options volumes are now more than 5 times larger than that of Europe. By comparison, options activity in these two markets moved in tandem before 2022. The US options market boom is unprecedented.",
      "summary": "<p>Risk appetite is reaching historic levels:<br />\n<br />\nThe 10-day moving average of S&amp;P 500 options volume is up to a record ~5.5 million contracts.<br />\n<br />\nSince 2022, this figure has more than TRIPLED.<br />\n<br />\nOver the same period, Euro Stoxx 50 options volume has remained roughly unchanged, near ~1 million contracts.<br />\n<br />\nAs a result, US options volumes are now more th",
      "link": "https://nitter.net/KobeissiLetter/status/2076808376550305879#m",
      "published": "2026-07-13T23:17:56+00:00",
      "score": 1
    },
    {
      "source": "Walter Bloomberg",
      "category": "twitter",
      "title": "TRUMP PROPOSES 20% FEE ON CARGO SHIPPED THROUGH STRAIT OF HORMUZ: SEMAFOR US REIMPOSED NAVAL BLOCKADE ON IRAN, TRUMP FORMALLY NOTIFIED CONGRESS: SEMAFOR",
      "summary": "<p>TRUMP PROPOSES 20% FEE ON CARGO SHIPPED THROUGH STRAIT OF HORMUZ: SEMAFOR <br />\n<br />\nUS REIMPOSED NAVAL BLOCKADE ON IRAN, TRUMP FORMALLY NOTIFIED CONGRESS: SEMAFOR</p>",
      "link": "https://nitter.net/DeItaone/status/2076801496960630815#m",
      "published": "2026-07-13T22:50:36+00:00",
      "score": 1
    },
    {
      "source": "Walter Bloomberg",
      "category": "twitter",
      "title": "Pinned: IRAN WAR RESUMES — HORMUZ OUTLOOK WORSENS Trump has formally notified Congress that U.S. hostilities against Iran have resumed, claiming a new 60-day military window. As Washington reinstates its blockade, Kalshi puts the chance of Hormuz traffic normalizing before 2027 at just 46%. https://kalshi.com/markets/kxhormuznorm/when-will-traffic-at-the-strait-of-hormuz-return-to-normal/kxhormuznorm-26mar17",
      "summary": "<p>IRAN WAR RESUMES — HORMUZ OUTLOOK WORSENS<br />\n<br />\nTrump has formally notified Congress that U.S. hostilities against Iran have resumed, claiming a new 60-day military window.<br />\n<br />\nAs Washington reinstates its blockade, Kalshi puts the chance of Hormuz traffic normalizing before 2027 at just 46%.<br />\n<br />\n<a href=\"https://kalshi.com/markets/kxhormuznorm/when-will-traffic-at-the-",
      "link": "https://nitter.net/DeItaone/status/2076801077693870364#m",
      "published": "2026-07-13T22:48:56+00:00",
      "score": 1
    },
    {
      "source": "Walter Bloomberg",
      "category": "twitter",
      "title": "TRUMP DEMANDS 20% HORMUZ CARGO FEE President Trump is proposing a 20% charge on cargo shipped through the Strait of Hormuz—about $30 million for a fully loaded oil supertanker. The shipping industry reacted with surprise, citing no warning or details. Iran’s foreign minister agreed secure passage should be compensated but called 20% excessive. Hormuz carries roughly one-fifth of global oil and gas flows.",
      "summary": "<p>TRUMP DEMANDS 20% HORMUZ CARGO FEE<br />\n<br />\nPresident Trump is proposing a 20% charge on cargo shipped through the Strait of Hormuz—about $30 million for a fully loaded oil supertanker.<br />\n<br />\nThe shipping industry reacted with surprise, citing no warning or details.<br />\n<br />\nIran’s foreign minister agreed secure passage should be compensated but called 20% excessive.<br />\n<br />",
      "link": "https://nitter.net/DeItaone/status/2076798855408963654#m",
      "published": "2026-07-13T22:40:06+00:00",
      "score": 1
    },
    {
      "source": "Walter Bloomberg",
      "category": "twitter",
      "title": "TRUMP SIGNED REGULATORY RELIEF FOR ‘CERTAIN STATIONARY SOURCES’",
      "summary": "<p>TRUMP SIGNED REGULATORY RELIEF FOR ‘CERTAIN STATIONARY SOURCES’</p>",
      "link": "https://nitter.net/DeItaone/status/2076798040233443541#m",
      "published": "2026-07-13T22:36:52+00:00",
      "score": 1
    },
    {
      "source": "Walter Bloomberg",
      "category": "twitter",
      "title": "TRUMP ON IRAN: THINK A DEAL IS POSSIBLE",
      "summary": "<p>TRUMP ON IRAN: THINK A DEAL IS POSSIBLE</p>",
      "link": "https://nitter.net/DeItaone/status/2076791408803864827#m",
      "published": "2026-07-13T22:10:31+00:00",
      "score": 1
    },
    {
      "source": "Walter Bloomberg",
      "category": "twitter",
      "title": "TRUMP ON IRAN: WANT TO BE REIMBURSED FOR PROTECTING COUNTRIES THAT WE'RE HELPING IN STRAIT OF HORMUZ",
      "summary": "<p>TRUMP ON IRAN: WANT TO BE REIMBURSED FOR PROTECTING COUNTRIES THAT WE'RE HELPING IN STRAIT OF HORMUZ</p>",
      "link": "https://nitter.net/DeItaone/status/2076791361957769359#m",
      "published": "2026-07-13T22:10:20+00:00",
      "score": 1
    },
    {
      "source": "Walter Bloomberg",
      "category": "twitter",
      "title": "TRUMP ON IRAN: DOING ANOTHER MAJOR ATTACK MONDAY NIGHT",
      "summary": "<p>TRUMP ON IRAN: DOING ANOTHER MAJOR ATTACK MONDAY NIGHT</p>",
      "link": "https://nitter.net/DeItaone/status/2076791243724456048#m",
      "published": "2026-07-13T22:09:52+00:00",
      "score": 1
    },
    {
      "source": "Kobeissi Letter",
      "category": "twitter",
      "title": "BREAKING: President Trump has formally notified US Congress that the US is at war with Iran, per Politico. Details include: 1. The move gives Trump another 60 days to use the military in the region without congressional approval 2. Trump said strikes that began on July 7th represent \"military action consistent with my responsibility to protect Americans and US interests both at home and abroad\" 3. Trump also just said that he will \"hit Iran hard\" tonight amid mounting tensions The Iran War appears to be back again.",
      "summary": "<p>BREAKING: President Trump has formally notified US Congress that the US is at war with Iran, per Politico.<br />\n<br />\nDetails include:<br />\n<br />\n1. The move gives Trump another 60 days to use the military in the region without congressional approval<br />\n<br />\n2. Trump said strikes that began on July 7th represent \"military action consistent with my responsibility to protect Americans an",
      "link": "https://nitter.net/KobeissiLetter/status/2076777484775985242#m",
      "published": "2026-07-13T21:15:11+00:00",
      "score": 1
    },
    {
      "source": "Walter Bloomberg",
      "category": "twitter",
      "title": "OIL SURGES AS TRUMP SAYS US WANTS 20% CHARGE FOR HORMUZ FLOW",
      "summary": "<p>OIL SURGES AS TRUMP SAYS US WANTS 20% CHARGE FOR HORMUZ FLOW</p>",
      "link": "https://nitter.net/DeItaone/status/2076765994140225892#m",
      "published": "2026-07-13T20:29:32+00:00",
      "score": 1
    },
    {
      "source": "r/Forex",
      "category": "reddit",
      "title": "Why you should be looking at DXY for market structure",
      "summary": "<table> <tr><td> <a href=\"https://www.reddit.com/r/Forex/comments/1uvn8ba/why_you_should_be_looking_at_dxy_for_market/\"> <img alt=\"Why you should be looking at DXY for market structure\" src=\"https://preview.redd.it/ul8urbe342dh1.jpg?width=140&amp;height=140&amp;crop=1:1,smart&amp;auto=webp&amp;s=fae6735bbf4bdfb24ccf4ed8e179e804f2e71c1a\" title=\"Why you should be looking at DXY for market structure\"",
      "link": "https://www.reddit.com/r/Forex/comments/1uvn8ba/why_you_should_be_looking_at_dxy_for_market/",
      "published": "2026-07-13T20:28:16+00:00",
      "score": 2
    },
    {
      "source": "Walter Bloomberg",
      "category": "twitter",
      "title": "TRUMP ON IRAN: WE ARE GOING TO TAKE OUT PICKAXE MOUNTAIN -HUGH HEWITT SHOW",
      "summary": "<p>TRUMP ON IRAN: WE ARE GOING TO TAKE OUT PICKAXE MOUNTAIN -HUGH HEWITT SHOW</p>",
      "link": "https://nitter.net/DeItaone/status/2076765517814136914#m",
      "published": "2026-07-13T20:27:38+00:00",
      "score": 1
    },
    {
      "source": "Walter Bloomberg",
      "category": "twitter",
      "title": "SMARTPHONE SHIPMENTS HIT A 13-YEAR LOW Global smartphone shipments fell 11% in Q2, reaching their lowest level for the period since 2013. A memory chip shortage has pushed up phone prices and weakened demand, hitting Xiaomi, Oppo, and Vivo hardest. Samsung regained the top position, while Apple reached a record 20% global market share. Meanwhile, strong AI-driven demand continues to benefit memory chipmakers.",
      "summary": "<p>SMARTPHONE SHIPMENTS HIT A 13-YEAR LOW<br />\n<br />\nGlobal smartphone shipments fell 11% in Q2, reaching their lowest level for the period since 2013.<br />\n<br />\nA memory chip shortage has pushed up phone prices and weakened demand, hitting Xiaomi, Oppo, and Vivo hardest.<br />\n<br />\nSamsung regained the top position, while Apple reached a record 20% global market share.<br />\n<br />\nMeanwhi",
      "link": "https://nitter.net/DeItaone/status/2076764884453482872#m",
      "published": "2026-07-13T20:25:07+00:00",
      "score": 1
    },
    {
      "source": "Walter Bloomberg",
      "category": "twitter",
      "title": "TRUMP: I DISAGREE WITH NETANYAHU SOMETIMES AND I LET HIM KNOW",
      "summary": "<p>TRUMP: I DISAGREE WITH NETANYAHU SOMETIMES AND I LET HIM KNOW</p>",
      "link": "https://nitter.net/DeItaone/status/2076762452620972429#m",
      "published": "2026-07-13T20:15:27+00:00",
      "score": 1
    },
    {
      "source": "Kobeissi Letter",
      "category": "twitter",
      "title": "BREAKING: President Trump’s Thursday speech is reportedly to address “newly declassified intelligence reports related to foreign interference in the 2020 election,” per MS NOW.",
      "summary": "<p>BREAKING: President Trump’s Thursday speech is reportedly to address “newly declassified intelligence reports related to foreign interference in the 2020 election,” per MS NOW.</p>\n<hr />\n<blockquote>\n<b>The Kobeissi Letter (@KobeissiLetter)</b>\n<p>\n<p>BREAKING: President Trump says he will be addressing the nation on Thursday at 9 PM ET.</p>\n<img src=\"https://nitter.net/pic/media%2FHNIRa52WMAA",
      "link": "https://nitter.net/KobeissiLetter/status/2076755890695221526#m",
      "published": "2026-07-13T19:49:23+00:00",
      "score": 1
    },
    {
      "source": "Kobeissi Letter",
      "category": "twitter",
      "title": "BREAKING: President Trump says he will be addressing the nation on Thursday at 9 PM ET.",
      "summary": "<p>BREAKING: President Trump says he will be addressing the nation on Thursday at 9 PM ET.</p>\n<img src=\"https://nitter.net/pic/media%2FHNIRa52WMAAcaxA.jpg\" />",
      "link": "https://nitter.net/KobeissiLetter/status/2076753955418210379#m",
      "published": "2026-07-13T19:41:41+00:00",
      "score": 1
    },
    {
      "source": "Kobeissi Letter",
      "category": "twitter",
      "title": "BREAKING: Iran’s Foreign Minister Araghchi responds to President Trump announcing a 20% fee to transit the Strait of Hormuz: “POTUS is absolutely right. Whoever provides secure and safe passage of commercial vessels through the Strait of Hormuz should be compensated for this service. Iran has always been the guardian of the Strait and will remain so forever. 20% is of course too much. We will be fair,” he says.",
      "summary": "<p>BREAKING: Iran’s Foreign Minister Araghchi responds to President Trump announcing a 20% fee to transit the Strait of Hormuz:<br />\n<br />\n“POTUS is absolutely right. Whoever provides secure and safe passage of commercial vessels through the Strait of Hormuz should be compensated for this service. <br />\n<br />\nIran has always been the guardian of the Strait and will remain so forever.<br />\n<br",
      "link": "https://nitter.net/KobeissiLetter/status/2076742442812842203#m",
      "published": "2026-07-13T18:55:57+00:00",
      "score": 1
    },
    {
      "source": "Kobeissi Letter",
      "category": "twitter",
      "title": "BREAKING: US oil prices surge +9% after President Trump announces the US is reimposing its blockade of the Strait of Hormuz, with ships now required to pay a fee equal to 20% of their cargo’s value to transit the waterway.",
      "summary": "<p>BREAKING: US oil prices surge +9% after President Trump announces the US is reimposing its blockade of the Strait of Hormuz, with ships now required to pay a fee equal to 20% of their cargo’s value to transit the waterway.</p>\n<img src=\"https://nitter.net/pic/media%2FHNIE4zYXIAAriFy.jpg\" />",
      "link": "https://nitter.net/KobeissiLetter/status/2076727756537090211#m",
      "published": "2026-07-13T17:57:35+00:00",
      "score": 1
    },
    {
      "source": "Kobeissi Letter",
      "category": "twitter",
      "title": "BREAKING: Total US federal debt is now up to a record $39.4 trillion, rising +$3.2 trillion over the last 12 months. Since 2020, US federal debt is now up a massive +$16.3 trillion. This marks a +$2.5 trillion average annual increase, or +$209 billion per month. At this pace, total US debt will surge to $50.0 trillion before 2030. The US debt crisis has no end in sight.",
      "summary": "<p>BREAKING: Total US federal debt is now up to a record $39.4 trillion, rising +$3.2 trillion over the last 12 months.<br />\n<br />\nSince 2020, US federal debt is now up a massive +$16.3 trillion.<br />\n<br />\nThis marks a +$2.5 trillion average annual increase, or +$209 billion per month.<br />\n<br />\nAt this pace, total US debt will surge to $50.0 trillion before 2030.<br />\n<br />\nThe US debt ",
      "link": "https://nitter.net/KobeissiLetter/status/2076718083150852328#m",
      "published": "2026-07-13T17:19:09+00:00",
      "score": 1
    },
    {
      "source": "Kobeissi Letter",
      "category": "twitter",
      "title": "BREAKING: President Trump says the US is reinstating its blockade of the Strait of Hormuz for Iranian ships and customers. Trump says the US will now be known as \"The Guardian of the Strait of Hormuz\" and will be \"reimbursed\" at a rate of 20% on all cargo shipped. It appears the US is now imposing a blockade and fees to transit the Strait of Hormuz.",
      "summary": "<p>BREAKING: President Trump says the US is reinstating its blockade of the Strait of Hormuz for Iranian ships and customers.<br />\n<br />\nTrump says the US will now be known as \"The Guardian of the Strait of Hormuz\" and will be \"reimbursed\" at a rate of 20% on all cargo shipped.<br />\n<br />\nIt appears the US is now imposing a blockade and fees to transit the Strait of Hormuz.</p>\n<img src=\"https",
      "link": "https://nitter.net/KobeissiLetter/status/2076673692407394643#m",
      "published": "2026-07-13T14:22:45+00:00",
      "score": 1
    },
    {
      "source": "r/Forex",
      "category": "reddit",
      "title": "Is it safe to trade Gold/Silver futures on Non-KYC platforms?",
      "summary": "<!-- SC_OFF --><div class=\"md\"><p>Hey guys,</p> <p>Have an idea of trading Gold/Silver futures but on Non-KYC platforms. Want to find a platform which requires No KYC also there is a small change of blocking account if I use a bot. </p> <p>Any experience with such kind of platforms? Also is it safe to trade there? </p> </div><!-- SC_ON --> &#32; submitted by &#32; <a href=\"https://www.reddit.com/u",
      "link": "https://www.reddit.com/r/Forex/comments/1uvag6w/is_it_safe_to_trade_goldsilver_futures_on_nonkyc/",
      "published": "2026-07-13T12:41:11+00:00",
      "score": 2
    },
    {
      "source": "Kobeissi Letter",
      "category": "twitter",
      "title": "BREAKING: President Trump says the United States is \"taking over\" the Strait of Hormuz. Brent crude oil prices extend gains to rise above $79/barrel.",
      "summary": "<p>BREAKING: President Trump says the United States is \"taking over\" the Strait of Hormuz.<br />\n<br />\nBrent crude oil prices extend gains to rise above $79/barrel.</p>",
      "link": "https://nitter.net/KobeissiLetter/status/2076642381554720796#m",
      "published": "2026-07-13T12:18:20+00:00",
      "score": 1
    },
    {
      "source": "r/Forex",
      "category": "reddit",
      "title": "DXY, GU and EU outlook",
      "summary": "<table> <tr><td> <a href=\"https://www.reddit.com/r/Forex/comments/1uv8tvf/dxy_gu_and_eu_outlook/\"> <img alt=\"DXY, GU and EU outlook\" src=\"https://preview.redd.it/99irzjmcfzch1.jpg?width=140&amp;height=68&amp;auto=webp&amp;s=c08c7a06af2f38b1f1cda4caed65c36bdce99a22\" title=\"DXY, GU and EU outlook\" /> </a> </td><td> <!-- SC_OFF --><div class=\"md\"><p>#DXY looking Bearish now,,, i am looking for those ",
      "link": "https://www.reddit.com/r/Forex/comments/1uv8tvf/dxy_gu_and_eu_outlook/",
      "published": "2026-07-13T11:26:01+00:00",
      "score": 2
    },
    {
      "source": "r/Forex",
      "category": "reddit",
      "title": "Gold finally broke its week-long range overnight — and the interesting part is it fell WHILE the Iran war escalated, not because it calmed down",
      "summary": "<!-- SC_OFF --><div class=\"md\"><p>So the range half of us have been watching for a week finally gave way. Gold had been locked in roughly 4088-4134 the whole week, and on the Sunday reopen it just went — sliced the 4088 floor, gave one last failed pop back up into the range, then dumped about 70 dollars to ~4044 before catching a small bounce. Clean breakdown, not a stop-run wick: it's now trading",
      "link": "https://www.reddit.com/r/Forex/comments/1uv4i1e/gold_finally_broke_its_weeklong_range_overnight/",
      "published": "2026-07-13T07:22:37+00:00",
      "score": 7
    },
    {
      "source": "r/Forex",
      "category": "reddit",
      "title": "Trade breakdown Gold",
      "summary": "<table> <tr><td> <a href=\"https://www.reddit.com/r/Forex/comments/1uv2q72/trade_breakdown_gold/\"> <img alt=\"Trade breakdown Gold\" src=\"https://preview.redd.it/pzpz44x5qxch1.jpeg?width=640&amp;crop=smart&amp;auto=webp&amp;s=2325e7750ee14a94bdc4006c942abdd09b8995e4\" title=\"Trade breakdown Gold\" /> </a> </td><td> <!-- SC_OFF --><div class=\"md\"><p>The market had a clear 1H (FVG) in focus. Price retrac",
      "link": "https://www.reddit.com/r/Forex/comments/1uv2q72/trade_breakdown_gold/",
      "published": "2026-07-13T05:43:04+00:00",
      "score": 1
    },
    {
      "source": "Kobeissi Letter",
      "category": "twitter",
      "title": "BREAKING: US stock market futures open slightly lower after Iran declares the Strait of Hormuz closed again: 1. S&P 500: -0.1% 2. Nasdaq 100: -0.3% 3. Dow Jones: -0.1% 4. WTI Crude: +3.0% 5. Brent: +2.5% 6. Gold: -0.3% The \"Memorandum of Understanding\" appears to have come to an end.",
      "summary": "<p>BREAKING: US stock market futures open slightly lower after Iran declares the Strait of Hormuz closed again:<br />\n<br />\n1. S&amp;P 500: -0.1%<br />\n2. Nasdaq 100: -0.3%<br />\n3. Dow Jones: -0.1%<br />\n4. WTI Crude: +3.0%<br />\n5. Brent: +2.5%<br />\n6. Gold: -0.3%<br />\n<br />\nThe \"Memorandum of Understanding\" appears to have come to an end.</p>",
      "link": "https://nitter.net/KobeissiLetter/status/2076426843725377908#m",
      "published": "2026-07-12T22:01:52+00:00",
      "score": 3
    },
    {
      "source": "r/Forex",
      "category": "reddit",
      "title": "Could Gold (XAUUSD) reach $10,000 by February 2028? My long-term supply & demand thesis.",
      "summary": "<table> <tr><td> <a href=\"https://www.reddit.com/r/Forex/comments/1uunr35/could_gold_xauusd_reach_10000_by_february_2028_my/\"> <img alt=\"Could Gold (XAUUSD) reach $10,000 by February 2028? My long-term supply &amp; demand thesis.\" src=\"https://preview.redd.it/prv29x94fuch1.png?width=640&amp;crop=smart&amp;auto=webp&amp;s=72ea90ad15e3265f09a0fbaf6adcde531d582f17\" title=\"Could Gold (XAUUSD) reach $1",
      "link": "https://www.reddit.com/r/Forex/comments/1uunr35/could_gold_xauusd_reach_10000_by_february_2028_my/",
      "published": "2026-07-12T18:41:36+00:00",
      "score": 6
    },
    {
      "source": "Kobeissi Letter",
      "category": "twitter",
      "title": "The Kobeissi Letter for the week of July 13th has been published and may be viewed through the link below: https://tinyurl.com/TheKobeissiLetter The Chart of the Week for the week of July 13th has been published. View or sign up for FREE through the link below: https://tinyurl.com/TKLChartofWeek",
      "summary": "<p>The Kobeissi Letter for the week of July 13th has been published and may be viewed through the link below:<br />\n<br />\n<a href=\"https://tinyurl.com/TheKobeissiLetter\">tinyurl.com/TheKobeissiLette…</a><br />\n<br />\nThe Chart of the Week for the week of July 13th has been published. View or sign up for FREE through the link below:<br />\n<br />\n<a href=\"https://tinyurl.com/TKLChartofWeek\">tinyurl",
      "link": "https://nitter.net/KobeissiLetter/status/2076373526299177137#m",
      "published": "2026-07-12T18:30:00+00:00",
      "score": 1
    },
    {
      "source": "Federal Reserve",
      "category": "macro",
      "title": "Federal Reserve announces the leadership and objectives of its task forces to advance the conduct of monetary policy",
      "summary": "Federal Reserve announces the leadership and objectives of its task forces to advance the conduct of monetary policy",
      "link": "https://www.federalreserve.gov/newsevents/pressreleases/monetary20260709a.htm",
      "published": "2026-07-09T19:00:00+00:00",
      "score": 1
    },
    {
      "source": "Federal Reserve",
      "category": "macro",
      "title": "Federal Reserve Board issues enforcement action with TS Banking Group, Inc. and TS Contrarian Bancshares, Inc.",
      "summary": "Federal Reserve Board issues enforcement action with TS Banking Group, Inc. and TS Contrarian Bancshares, Inc.",
      "link": "https://www.federalreserve.gov/newsevents/pressreleases/enforcement20260709a.htm",
      "published": "2026-07-09T15:00:00+00:00",
      "score": 1
    },
    {
      "source": "Federal Reserve",
      "category": "macro",
      "title": "Minutes of the Federal Open Market Committee, June 16-17, 2026",
      "summary": "Minutes of the Federal Open Market Committee, June 16-17, 2026",
      "link": "https://www.federalreserve.gov/newsevents/pressreleases/monetary20260708a.htm",
      "published": "2026-07-08T18:00:00+00:00",
      "score": 1
    },
    {
      "source": "Federal Reserve",
      "category": "macro",
      "title": "Federal Reserve Board requests comment on a proposal to amend its requirements for banks to maintain anti-money laundering programs",
      "summary": "Federal Reserve Board requests comment on a proposal to amend its requirements for banks to maintain anti-money laundering programs",
      "link": "https://www.federalreserve.gov/newsevents/pressreleases/bcreg20260707a.htm",
      "published": "2026-07-07T19:00:00+00:00",
      "score": 1
    },
    {
      "source": "Federal Reserve",
      "category": "macro",
      "title": "Federal Reserve Board issues enforcement action with Small Business Bank and announces termination enforcement actions with BNP Paribas S.A., BNP Paribas USA, Inc., BNP Paribas Securities Corp., and Community Bankshares, Inc.",
      "summary": "Federal Reserve Board issues enforcement action with Small Business Bank and announces termination enforcement actions with BNP Paribas S.A., BNP Paribas USA, Inc., BNP Paribas Securities Corp., and Community Bankshares, Inc.",
      "link": "https://www.federalreserve.gov/newsevents/pressreleases/enforcement20260702a.htm",
      "published": "2026-07-02T15:00:00+00:00",
      "score": 1
    },
    {
      "source": "Federal Reserve",
      "category": "macro",
      "title": "Federal Reserve issues initial findings from its 2025 triennial payments study",
      "summary": "Federal Reserve issues initial findings from its 2025 triennial payments study",
      "link": "https://www.federalreserve.gov/newsevents/pressreleases/other20260701a.htm",
      "published": "2026-07-01T18:30:00+00:00",
      "score": 1
    },
    {
      "source": "Federal Reserve",
      "category": "macro",
      "title": "Federal Reserve Board announces termination of enforcement action with Jiko Group, Inc.",
      "summary": "Federal Reserve Board announces termination of enforcement action with Jiko Group, Inc.",
      "link": "https://www.federalreserve.gov/newsevents/pressreleases/enforcement20260625a.htm",
      "published": "2026-06-25T15:00:00+00:00",
      "score": 1
    },
    {
      "source": "Federal Reserve",
      "category": "macro",
      "title": "Federal Reserve Board issues enforcement action with employee of Bank of Eufaula and S N B Bancshares, Inc.",
      "summary": "Federal Reserve Board issues enforcement action with employee of Bank of Eufaula and S N B Bancshares, Inc.",
      "link": "https://www.federalreserve.gov/newsevents/pressreleases/enforcement20260625b.htm",
      "published": "2026-06-25T15:00:00+00:00",
      "score": 1
    },
    {
      "source": "Federal Reserve",
      "category": "macro",
      "title": "Federal Reserve Board's annual bank stress test confirms that large banks are well positioned to weather a severe recession and able to continue to lend to households and businesses",
      "summary": "Federal Reserve Board's annual bank stress test confirms that large banks are well positioned to weather a severe recession and able to continue to lend to households and businesses",
      "link": "https://www.federalreserve.gov/newsevents/pressreleases/bcreg20260624a.htm",
      "published": "2026-06-24T20:00:00+00:00",
      "score": 1
    },
    {
      "source": "Federal Reserve",
      "category": "macro",
      "title": "Federal Reserve notes with deep sadness the passing of Alan Greenspan",
      "summary": "Federal Reserve notes with deep sadness the passing of Alan Greenspan",
      "link": "https://www.federalreserve.gov/newsevents/pressreleases/other20260622a.htm",
      "published": "2026-06-22T12:45:00+00:00",
      "score": 1
    },
    {
      "source": "Federal Reserve",
      "category": "macro",
      "title": "Federal Reserve Board issues enforcement action with former employee of Bank of Eufaula and S N B Bancshares, Inc.",
      "summary": "Federal Reserve Board issues enforcement action with former employee of Bank of Eufaula and S N B Bancshares, Inc.",
      "link": "https://www.federalreserve.gov/newsevents/pressreleases/enforcement20260618b.htm",
      "published": "2026-06-18T19:00:00+00:00",
      "score": 1
    },
    {
      "source": "Federal Reserve",
      "category": "macro",
      "title": "Federal Reserve Board issues enforcement action with former employee of Manufacturers and Traders Trust Company",
      "summary": "Federal Reserve Board issues enforcement action with former employee of Manufacturers and Traders Trust Company",
      "link": "https://www.federalreserve.gov/newsevents/pressreleases/enforcement20260618a.htm",
      "published": "2026-06-18T15:00:00+00:00",
      "score": 1
    },
    {
      "source": "Federal Reserve",
      "category": "macro",
      "title": "Federal Reserve Board requests comment on proposal to require certain payment stablecoin issuers to maintain an effective customer identification program",
      "summary": "Federal Reserve Board requests comment on proposal to require certain payment stablecoin issuers to maintain an effective customer identification program",
      "link": "https://www.federalreserve.gov/newsevents/pressreleases/bcreg20260618a.htm",
      "published": "2026-06-18T13:00:00+00:00",
      "score": 1
    },
    {
      "source": "Federal Reserve",
      "category": "macro",
      "title": "Federal Reserve issues FOMC statement",
      "summary": "Federal Reserve issues FOMC statement",
      "link": "https://www.federalreserve.gov/newsevents/pressreleases/monetary20260617a.htm",
      "published": "2026-06-17T18:00:00+00:00",
      "score": 2
    },
    {
      "source": "Federal Reserve",
      "category": "macro",
      "title": "Federal Reserve Board and Federal Open Market Committee release economic projections from the June 16-17 FOMC meeting",
      "summary": "Federal Reserve Board and Federal Open Market Committee release economic projections from the June 16-17 FOMC meeting",
      "link": "https://www.federalreserve.gov/newsevents/pressreleases/monetary20260617b.htm",
      "published": "2026-06-17T18:00:00+00:00",
      "score": 2
    },
    {
      "source": "Federal Reserve",
      "category": "macro",
      "title": "Federal Reserve Board announces final rule that establishes data standards for certain information collections",
      "summary": "Federal Reserve Board announces final rule that establishes data standards for certain information collections",
      "link": "https://www.federalreserve.gov/newsevents/pressreleases/bcreg20260611a.htm",
      "published": "2026-06-11T15:00:00+00:00",
      "score": 1
    },
    {
      "source": "Federal Reserve",
      "category": "macro",
      "title": "Federal Reserve Board announces that results from its annual bank stress test will be released on Wednesday, June 24, at 4 p.m. EDT.",
      "summary": "Federal Reserve Board announces that results from its annual bank stress test will be released on Wednesday, June 24, at 4 p.m. EDT.",
      "link": "https://www.federalreserve.gov/newsevents/pressreleases/bcreg20260609a.htm",
      "published": "2026-06-09T20:00:00+00:00",
      "score": 1
    },
    {
      "source": "Federal Reserve",
      "category": "macro",
      "title": "Federal Reserve Board issues enforcement actions with former employee of Atlantic Union Bank and former employee of Frost Bank",
      "summary": "Federal Reserve Board issues enforcement actions with former employee of Atlantic Union Bank and former employee of Frost Bank",
      "link": "https://www.federalreserve.gov/newsevents/pressreleases/enforcement20260528a.htm",
      "published": "2026-05-28T15:00:00+00:00",
      "score": 1
    }
  ],
  "errors": []
}